excel_operation/__init__.py
excel_operation/excel.py
instruments/DP821A.py
instruments/Multimemter.py
instruments/SMU_Examples.py
instruments/__init__.py
instruments/device_scan.py
instruments/instruments_name.py
instruments/smu_keithley_2450.py
one/__init__.py
one/hello.py
one/main.py
PypiInstruments-1.0.13.dist-info/METADATA
PypiInstruments-1.0.13.dist-info/WHEEL
PypiInstruments-1.0.13.dist-info/top_level.txt
PypiInstruments-1.0.13.dist-info/RECORD
