Metadata-Version: 2.1
Name: PypiInstruments
Version: 1.0.13
Summary: my package
